[
  {
    "id": "ch02-q1",
    "topic": "val immutability",
    "difficulty": "easy",
    "chapter": "ch-02",
    "snippet": "val score = 100\nscore = 200\nprintln(score)",
    "question": "What happens when this code is compiled?",
    "choices": [
      "Prints 100",
      "Prints 200",
      "Prints 300",
      "Compilation error — val cannot be reassigned"
    ],
    "correctIndex": 3,
    "explanation": {
      "summary": "`val` declares a read-only variable. After the first assignment, it cannot be changed. The compiler rejects `score = 200`.",
      "lineByLine": [
        "`val score = 100` — declares score as read-only with value 100.",
        "`score = 200` — illegal! val cannot be reassigned. Compiler error here.",
        "`println` is never reached."
      ],
      "tip": "AI-generated Kotlin strongly prefers `val` over `var`. Most variables you'll see are `val`. This is intentional — immutability reduces bugs."
    }
  },
  {
    "id": "ch02-q2",
    "topic": "var mutability",
    "difficulty": "easy",
    "chapter": "ch-02",
    "snippet": "var count = 0\ncount = count + 1\ncount = count + 1\nprintln(count)",
    "question": "What does this code print?",
    "choices": [
      "0",
      "1",
      "2",
      "Compilation error"
    ],
    "correctIndex": 2,
    "explanation": {
      "summary": "`var` declares a mutable variable. It can be reassigned as many times as needed.",
      "lineByLine": [
        "`var count = 0` — starts at 0.",
        "`count = count + 1` — count becomes 1.",
        "`count = count + 1` — count becomes 2.",
        "`println(2)` — prints 2."
      ],
      "tip": "Use `var` only when the value genuinely needs to change over time. In AI code, `var` appears far less often than `val` — its presence signals intentional mutation."
    }
  },
  {
    "id": "ch02-q3",
    "topic": "type inference",
    "difficulty": "easy",
    "chapter": "ch-02",
    "snippet": "val name = \"Alice\"\nval age = 30\nval height = 5.9\nprintln(name)",
    "question": "What type does Kotlin infer for `height`?",
    "choices": [
      "Int",
      "Float",
      "Double",
      "String"
    ],
    "correctIndex": 2,
    "explanation": {
      "summary": "Kotlin infers types from the assigned value. A decimal literal like `5.9` is inferred as `Double` by default.",
      "lineByLine": [
        "`val name = \"Alice\"` — inferred as String.",
        "`val age = 30` — inferred as Int.",
        "`val height = 5.9` — inferred as Double (all decimal literals are Double by default).",
        "`println(name)` — prints Alice."
      ],
      "tip": "Kotlin's type inference means you rarely need to write the type explicitly. But understanding what type gets inferred is important when reading AI code — `5.9` is a Double, `5.9f` is a Float."
    }
  },
  {
    "id": "ch02-q4",
    "topic": "explicit type annotation",
    "difficulty": "easy",
    "chapter": "ch-02",
    "snippet": "val x: Int = 10\nval y: Double = 10.0\nprintln(x + y)",
    "question": "What does this code print?",
    "choices": [
      "20",
      "20.0",
      "Compilation error — cannot add Int and Double",
      "10 + 10.0"
    ],
    "correctIndex": 1,
    "explanation": {
      "summary": "Kotlin does not implicitly convert between numeric types. But `x + y` here works because Kotlin promotes the Int to Double for the addition, yielding a Double result.",
      "lineByLine": [
        "`val x: Int = 10` — explicit Int annotation.",
        "`val y: Double = 10.0` — explicit Double annotation.",
        "`x + y` — x is promoted to Double, result is 20.0.",
        "`println(20.0)` — prints 20.0."
      ],
      "tip": "When Int and Double interact in arithmetic, the result is always Double. AI code uses explicit type annotations when inference might be ambiguous or when clarity matters."
    }
  },
  {
    "id": "ch02-q5",
    "topic": "val vs var choice",
    "difficulty": "easy",
    "chapter": "ch-02",
    "snippet": "fun main() {\n    val message: String\n    message = \"Hello\"\n    println(message)\n}",
    "question": "What does this code print?",
    "choices": [
      "Compilation error — val must be initialized at declaration",
      "Hello",
      "null",
      "message"
    ],
    "correctIndex": 1,
    "explanation": {
      "summary": "`val` can be declared without an immediate value as long as it's assigned exactly once before first use. This is called a deferred initialization.",
      "lineByLine": [
        "`val message: String` — declared without a value (type must be explicit here).",
        "`message = \"Hello\"` — assigned exactly once. This is valid for `val`.",
        "`println(message)` — prints Hello."
      ],
      "tip": "Deferred `val` initialization is common in AI code for variables assigned inside `when` branches or conditional logic. The compiler verifies it's assigned before use."
    }
  },
  {
    "id": "ch02-q6",
    "topic": "compound assignment",
    "difficulty": "easy",
    "chapter": "ch-02",
    "snippet": "var score = 10\nscore += 5\nscore += 3\nprintln(score)",
    "question": "What does this print?",
    "choices": [
      "10",
      "15",
      "18",
      "Compilation error"
    ],
    "correctIndex": 2,
    "explanation": {
      "summary": "`+=` is shorthand for `score = score + value`. It requires a `var` because it modifies the variable.",
      "lineByLine": [
        "`var score = 10` — starts at 10.",
        "`score += 5` → score = 10 + 5 = 15.",
        "`score += 3` → score = 15 + 3 = 18.",
        "`println(18)` — prints 18."
      ],
      "tip": "Kotlin supports all compound assignment operators: `+=`, `-=`, `*=`, `/=`, `%=`. They all require `var`. You'll see `count += 1` and `total += item.price` frequently in AI code."
    }
  },
  {
    "id": "ch02-q7",
    "topic": "increment operator",
    "difficulty": "easy",
    "chapter": "ch-02",
    "snippet": "var x = 0\nx++\nx++\nx++\nprintln(x)",
    "question": "What does this print?",
    "choices": [
      "0",
      "1",
      "3",
      "Compilation error — use x += 1 instead"
    ],
    "correctIndex": 2,
    "explanation": {
      "summary": "`x++` is the postfix increment operator — it increments `x` by 1. Called three times, x goes from 0 to 3.",
      "lineByLine": [
        "`var x = 0` — starts at 0.",
        "`x++` three times — each adds 1: 0 → 1 → 2 → 3.",
        "`println(3)` — prints 3."
      ],
      "tip": "`++` and `--` work in Kotlin just like other languages. `x++` and `++x` both increment by 1, but differ in what value they *return* when used in an expression. As a statement on its own, they behave identically."
    }
  },
  {
    "id": "ch02-q8",
    "topic": "Boolean inference",
    "difficulty": "easy",
    "chapter": "ch-02",
    "snippet": "val isLoggedIn = true\nval isAdmin = false\nprintln(isLoggedIn)\nprintln(isAdmin)",
    "question": "What does this print?",
    "choices": [
      "1 then 0",
      "true then false",
      "True then False",
      "Compilation error"
    ],
    "correctIndex": 1,
    "explanation": {
      "summary": "Kotlin infers `Boolean` from `true` or `false` literals. `println` on a Boolean prints its lowercase string form.",
      "lineByLine": [
        "`val isLoggedIn = true` — inferred as Boolean.",
        "`val isAdmin = false` — inferred as Boolean.",
        "`println(true)` — prints true (lowercase).",
        "`println(false)` — prints false (lowercase)."
      ],
      "tip": "Kotlin booleans print as lowercase `true` and `false`, not 1/0 or True/False. Boolean variable names in AI code typically start with `is`, `has`, `can`, or `should`."
    }
  },
  {
    "id": "ch02-q9",
    "topic": "Float literal",
    "difficulty": "easy",
    "chapter": "ch-02",
    "snippet": "val a = 3.14\nval b = 3.14f\nprintln(a)\nprintln(b)",
    "question": "What are the types of `a` and `b`?",
    "choices": [
      "Both are Double",
      "a is Double, b is Float",
      "a is Float, b is Double",
      "Both are Float"
    ],
    "correctIndex": 1,
    "explanation": {
      "summary": "A bare decimal literal like `3.14` is inferred as `Double`. Adding an `f` suffix forces it to `Float`, which has less precision.",
      "lineByLine": [
        "`val a = 3.14` — no suffix → inferred as Double (64-bit).",
        "`val b = 3.14f` — `f` suffix → inferred as Float (32-bit).",
        "Both print their values, but Float may show slight precision differences."
      ],
      "tip": "Always use `Double` unless you have a specific reason for `Float` (e.g., GPU data or memory-constrained arrays). AI code defaults to `Double` for all decimal values."
    }
  },
  {
    "id": "ch02-q10",
    "topic": "val vs var independence",
    "difficulty": "easy",
    "chapter": "ch-02",
    "snippet": "var a = 1\nvar b = a\na = 99\nprintln(a)\nprintln(b)",
    "question": "What does this print?",
    "choices": [
      "99 then 99",
      "99 then 1",
      "1 then 99",
      "Compilation error"
    ],
    "correctIndex": 1,
    "explanation": {
      "summary": "Assigning `b = a` copies the *value* of `a` at that moment. Later changes to `a` do not affect `b` — they are independent variables.",
      "lineByLine": [
        "`var a = 1` — a is 1.",
        "`var b = a` — b gets the current value of a, which is 1. b = 1.",
        "`a = 99` — a is now 99, but b is unchanged.",
        "`println(a)` → 99. `println(b)` → 1."
      ],
      "tip": "Assigning one variable to another copies its value for primitive types (Int, Boolean, etc.). This is called value semantics. Object references behave differently — but for basic types this is always a copy."
    }
  }
]